setup.cfg
setup.py
jira_issue_recommender/__init__.py
jira_issue_recommender/main.py
jira_issue_recommender/util.py
jira_issue_recommender.egg-info/PKG-INFO
jira_issue_recommender.egg-info/SOURCES.txt
jira_issue_recommender.egg-info/dependency_links.txt
jira_issue_recommender.egg-info/entry_points.txt
jira_issue_recommender.egg-info/requires.txt
jira_issue_recommender.egg-info/top_level.txt