Metadata-Version: 1.0
Name: jira-issue-recommender
Version: 0.0.3
Summary: Find related issues
Home-page: https://github.com/qsweber/jira-issue-recommender
Author: Quinn Weber
Author-email: quinn@quinnweber.com
License: UNKNOWN
Platform: UNKNOWN
